thyroai/__init__.py
thyroai/thyroAI.py
thyroai-0.1.0.dist-info/METADATA
thyroai-0.1.0.dist-info/WHEEL
thyroai-0.1.0.dist-info/RECORD
